mogi/__init__.py
mogi/admin.py
mogi/apps.py
mogi/filter.py
mogi/forms.py
mogi/models.py
mogi/serializers.py
mogi/sitetrees.py
mogi/tables.py
mogi/tasks.py
mogi/test_settings.py
mogi/tests.py
mogi/urls.py
mogi/views.py
mogi/migrations/0001_initial.py
mogi/migrations/__init__.py
mogi/static/__init__.py
mogi/static/archive/__init__.py
mogi/static/archive/jquery/AUTHORS.txt
mogi/static/archive/jquery/AUTHORS.txt.py
mogi/static/archive/jquery/LICENSE.txt
mogi/static/archive/jquery/LICENSE.txt.py
mogi/static/archive/jquery/README.md
mogi/static/archive/jquery/__init__.py
mogi/static/archive/jquery/bower.json
mogi/static/archive/jquery/external/__init__.py
mogi/static/archive/jquery/external/sizzle/LICENSE.txt
mogi/static/archive/jquery/external/sizzle/LICENSE.txt.py
mogi/static/archive/jquery/external/sizzle/__init__.py
mogi/static/archive/jquery/src/ajax.js
mogi/static/archive/jquery/src/attributes.js
mogi/static/archive/jquery/src/callbacks.js
mogi/static/archive/jquery/src/core.js
mogi/static/archive/jquery/src/css.js
mogi/static/archive/jquery/src/data.js
mogi/static/archive/jquery/src/deferred.js
mogi/static/archive/jquery/src/deprecated.js
mogi/static/archive/jquery/src/dimensions.js
mogi/static/archive/jquery/src/effects.js
mogi/static/archive/jquery/src/event.js
mogi/static/archive/jquery/src/jquery.js
mogi/static/archive/jquery/src/manipulation.js
mogi/static/archive/jquery/src/offset.js
mogi/static/archive/jquery/src/queue.js
mogi/static/archive/jquery/src/selector-native.js
mogi/static/archive/jquery/src/selector-sizzle.js
mogi/static/archive/jquery/src/selector.js
mogi/static/archive/jquery/src/serialize.js
mogi/static/archive/jquery/src/traversing.js
mogi/static/archive/jquery/src/wrap.js
mogi/static/archive/jquery/src/ajax/jsonp.js
mogi/static/archive/jquery/src/ajax/load.js
mogi/static/archive/jquery/src/ajax/parseXML.js
mogi/static/archive/jquery/src/ajax/script.js
mogi/static/archive/jquery/src/ajax/xhr.js
django_mogi-0.0.2.dist-info/LICENSE
django_mogi-0.0.2.dist-info/METADATA
django_mogi-0.0.2.dist-info/WHEEL
django_mogi-0.0.2.dist-info/top_level.txt
django_mogi-0.0.2.dist-info/RECORD
