Metadata-Version: 2.1
Name: django-mogi
Version: 0.0.2
Summary: Metabolomics Organisation with Galaxy and ISA
Home-page: https://mogi.readthedocs.io
Author: Thomas N lawson
Author-email: thomas.nigel.lawson@gmail.com
License: GNU License
Platform: UNKNOWN
Classifier: Environment :: Web Environment
Classifier: Framework :: Django
Classifier: Framework :: Django :: 1.11
Classifier: Intended Audience :: Developers
Classifier: License :: OSI Approved :: GNU General Public License v3 (GPLv3)
Classifier: Operating System :: OS Independent
Classifier: Programming Language :: Python
Classifier: Programming Language :: Python :: 2.7
Classifier: Programming Language :: Python :: 3.6
Classifier: Topic :: Internet :: WWW/HTTP
Classifier: Topic :: Internet :: WWW/HTTP :: Dynamic Content
Requires-Dist: django (>=1.11.15)
Requires-Dist: django-galaxy
Requires-Dist: django-misa
